odoo/addons/product_pricelist_simulation_margin/README.rst
odoo/addons/product_pricelist_simulation_margin/__init__.py
odoo/addons/product_pricelist_simulation_margin/__manifest__.py
odoo/addons/product_pricelist_simulation_margin/i18n/es.po
odoo/addons/product_pricelist_simulation_margin/i18n/fr.po
odoo/addons/product_pricelist_simulation_margin/i18n/it.po
odoo/addons/product_pricelist_simulation_margin/i18n/product_pricelist_simulation_margin.pot
odoo/addons/product_pricelist_simulation_margin/i18n/tr.po
odoo/addons/product_pricelist_simulation_margin/readme/CONTRIBUTORS.rst
odoo/addons/product_pricelist_simulation_margin/readme/DESCRIPTION.rst
odoo/addons/product_pricelist_simulation_margin/readme/USAGE.rst
odoo/addons/product_pricelist_simulation_margin/static/description/icon.png
odoo/addons/product_pricelist_simulation_margin/static/description/index.html
odoo/addons/product_pricelist_simulation_margin/static/description/product_template_form.png
odoo/addons/product_pricelist_simulation_margin/static/description/wizard_preview_pricelist_margin_form.png
odoo/addons/product_pricelist_simulation_margin/tests/__init__.py
odoo/addons/product_pricelist_simulation_margin/tests/test_module.py
odoo/addons/product_pricelist_simulation_margin/wizards/__init__.py
odoo/addons/product_pricelist_simulation_margin/wizards/wizard_preview_pricelist.py
odoo/addons/product_pricelist_simulation_margin/wizards/wizard_preview_pricelist_views.xml
odoo_addon_product_pricelist_simulation_margin-16.0.1.0.1.4.dist-info/METADATA
odoo_addon_product_pricelist_simulation_margin-16.0.1.0.1.4.dist-info/WHEEL
odoo_addon_product_pricelist_simulation_margin-16.0.1.0.1.4.dist-info/top_level.txt
odoo_addon_product_pricelist_simulation_margin-16.0.1.0.1.4.dist-info/RECORD
