Metadata-Version: 2.1
Name: odoo-addon-product_pricelist_simulation_margin
Version: 16.0.1.0.1.4
Summary: Add margin of product price for all pricelists
Home-page: https://github.com/OCA/product-attribute
Author: Odoo Community Association (OCA), FactorLibre
Author-email: support@odoo-community.org
License: AGPL-3
Classifier: Programming Language :: Python
Classifier: Framework :: Odoo
Classifier: Framework :: Odoo :: 16.0
Classifier: License :: OSI Approved :: GNU Affero General Public License v3
Requires-Python: >=3.10
Requires-Dist: odoo-addon-product-pricelist-simulation<16.1dev,>=16.0dev
Requires-Dist: odoo<16.1dev,>=16.0a
